{
    "href": "/content/meiju25835.html",
    "name": "青春期的我们第二季",
    "state": "第7集",
    "time": "2020-9-19",
    "tv": "Hulu"
}{
    "href": "/content/meiju25382.html",
    "name": "毒药第一季",
    "state": "第2集",
    "time": "2020-9-19",
    "tv": "其他"
}{
    "href": "/content/meiju25456.html",
    "name": "审讯对决第二季",
    "state": "本季终",
    "time": "2020-9-19",
    "tv": "BBC"
}{
    "href": "/content/meiju23469.html",
    "name": "梅森探案集第一季",
    "state": "第31集",
    "time": "2020-9-19",
    "tv": "CBS"
}{
    "href": "/content/meiju25828.html",
    "name": "两周后就死第一季",
    "state": "第3集",
    "time": "2020-9-19",
    "tv": "Sky-Go"
}{
    "href": "/content/meiju25834.html",
    "name": "间谍亚契第十一季",
    "state": "第2集",
    "time": "2020-9-19",
    "tv": "FX"
}{
    "href": "/content/meiju25629.html",
    "name": "疯狂教授生物课第三季",
    "state": "第2集",
    "time": "2020-9-18",
    "tv": "NBC"
}{
    "href": "/content/meiju25689.html",
    "name": "拉契特第一季",
    "state": "第8集",
    "time": "2020-9-18",
    "tv": "Netflix"
}{
    "href": "/content/meiju25761.html",
    "name": "玩物男孩第一季",
    "state": "第4集",
    "time": "2020-9-18",
    "tv": "其他"
}{
    "href": "/content/meiju25830.html",
    "name": "盖棺不定论第一季",
    "state": "第6集",
    "time": "2020-9-18",
    "tv": "Netflix"
}{
    "href": "/content/meiju25833.html",
    "name": "龙之信条第一季",
    "state": "第7集",
    "time": "2020-9-18",
    "tv": "Netflix"
}{
    "href": "/content/meiju25623.html",
    "name": "星际迷航：下层舰员第一季",
    "state": "第7集",
    "time": "2020-9-18",
    "tv": "CBS"
}{
    "href": "/content/meiju25635.html",
    "name": "足球教练第一季",
    "state": "第8集",
    "time": "2020-9-18",
    "tv": "AppleTV+"
}{
    "href": "/content/meiju25748.html",
    "name": "无声的证言第十七季",
    "state": "第10集",
    "time": "2020-9-18",
    "tv": "BBC"
}{
    "href": "/content/meiju25587.html",
    "name": "黑袍纠察队第二季",
    "state": "第5集",
    "time": "2020-9-18",
    "tv": "Amazon"
}{
    "href": "/content/meiju25742.html",
    "name": "生活觉醒第一季",
    "state": "第8集",
    "time": "2020-9-18",
    "tv": "Hulu"
}{
    "href": "/content/meiju25822.html",
    "name": "丹斯第一季",
    "state": "第3集",
    "time": "2020-9-18",
    "tv": "ITV"
}{
    "href": "/content/meiju25641.html",
    "name": "异星灾变第一季",
    "state": "第7集",
    "time": "2020-9-18",
    "tv": "HBO"
}{
    "href": "/content/meiju25832.html",
    "name": "塔可美食纪第二季",
    "state": "本季终",
    "time": "2020-9-17",
    "tv": "Netflix"
}{
    "href": "/content/meiju25831.html",
    "name": "塔可美食纪第一季",
    "state": "本季终",
    "time": "2020-9-17",
    "tv": "Netflix"
}{
    "href": "/content/meiju24964.html",
    "name": "地球百子第七季",
    "state": "第14集",
    "time": "2020-9-17",
    "tv": "CW"
}{
    "href": "/content/meiju25826.html",
    "name": "罗马宝贝第三季",
    "state": "第6集",
    "time": "2020-9-17",
    "tv": "Netflix"
}{
    "href": "/content/meiju25827.html",
    "name": "审讯室第二季",
    "state": "第4集",
    "time": "2020-9-17",
    "tv": "Netflix"
}{
    "href": "/content/meiju25779.html",
    "name": "万物既伟大又渺小第一季",
    "state": "第3集",
    "time": "2020-9-17",
    "tv": "Channel5"
}{
    "href": "/content/meiju25796.html",
    "name": "金牌评论员第三季",
    "state": "第2集",
    "time": "2020-9-17",
    "tv": "TLC"
}{
    "href": "/content/meiju25829.html",
    "name": "追迹第二季",
    "state": "第8集",
    "time": "2020-9-17",
    "tv": "AXN"
}{
    "href": "/content/meiju25741.html",
    "name": "来巴黎找我第三季",
    "state": "第3集",
    "time": "2020-9-16",
    "tv": "Hulu"
}{
    "href": "/content/meiju25616.html",
    "name": "本色第一季",
    "state": "第1集",
    "time": "2020-9-16",
    "tv": "HBO"
}{
    "href": "/content/meiju25436.html",
    "name": "从海底出击第二季",
    "state": "第4集",
    "time": "2020-9-16",
    "tv": "其他"
}{
    "href": "/content/meiju25825.html",
    "name": "迈罗·墨菲定律第二季",
    "state": "第1集",
    "time": "2020-9-16",
    "tv": "Disney"
}{
    "href": "/content/meiju24580.html",
    "name": "无声的证言第二十一季",
    "state": "第4集",
    "time": "2020-9-16",
    "tv": "BBC"
}{
    "href": "/content/meiju25066.html",
    "name": "牧师神探第五季",
    "state": "第5集",
    "time": "2020-9-16",
    "tv": "ITV"
}{
    "href": "/content/meiju24970.html",
    "name": "DC超级英雄美少女第一季",
    "state": "本季终",
    "time": "2020-9-16",
    "tv": "Cartoon-Network"
}{
    "href": "/content/meiju25679.html",
    "name": "温特沃斯第八季",
    "state": "第8集",
    "time": "2020-9-16",
    "tv": "其他"
}{
    "href": "/content/meiju25780.html",
    "name": "上帝之手第一季",
    "state": "第2集",
    "time": "2020-9-15",
    "tv": "Amazon-Prime"
}{
    "href": "/content/meiju25824.html",
    "name": "热血废柴中介第二季",
    "state": "第1集",
    "time": "2020-9-15",
    "tv": "Channel4"
}{
    "href": "/content/meiju25306.html",
    "name": "第三天第一季",
    "state": "第1集",
    "time": "2020-9-15",
    "tv": "HBO"
}{
    "href": "/content/meiju25782.html",
    "name": "淘气小女巫第一季",
    "state": "第3集",
    "time": "2020-9-15",
    "tv": "BBC"
}{
    "href": "/content/meiju25719.html",
    "name": "半独立屋第一季",
    "state": "第6集",
    "time": "2020-9-15",
    "tv": "BBC-TWO"
}{
    "href": "/content/meiju25712.html",
    "name": "权欲第二章",
    "state": "第2集",
    "time": "2020-9-15",
    "tv": "Starz"
}{
    "href": "/content/meiju25823.html",
    "name": "孤注一掷：托特纳姆热刺第一季",
    "state": "第9集",
    "time": "2020-9-15",
    "tv": "Amazon-Prime"
}{
    "href": "/content/meiju25774.html",
    "name": "神探斯特莱克第四季",
    "state": "第4集",
    "time": "2020-9-15",
    "tv": "BBC"
}{
    "href": "/content/meiju25576.html",
    "name": "恶魔之地第一季",
    "state": "第5集",
    "time": "2020-9-15",
    "tv": "HBO"
}{
    "href": "/content/meiju21657.html",
    "name": "法律与秩序第十七季",
    "state": "第18集",
    "time": "2020-9-14",
    "tv": "NBC"
}{
    "href": "/content/meiju25412.html",
    "name": "104号房间第四季",
    "state": "第8集",
    "time": "2020-9-14",
    "tv": "HBO"
}{
    "href": "/content/meiju19761.html",
    "name": "复仇者集结第一季",
    "state": "本季终",
    "time": "2020-9-14",
    "tv": "Disney"
}{
    "href": "/content/meiju25517.html",
    "name": "卧底第二季",
    "state": "第2集",
    "time": "2020-9-14",
    "tv": "Netflix"
}{
    "href": "/content/meiju25821.html",
    "name": "新鲜事儿第一季",
    "state": "第7集",
    "time": "2020-9-13",
    "tv": "其他"
}{
    "href": "/content/meiju23398.html",
    "name": "天佑吾王第一季",
    "state": "第71集",
    "time": "2020-9-13",
    "tv": "其他"
}{
    "href": "/content/meiju25812.html",
    "name": "茱莉与魅影男孩第一季",
    "state": "本季终",
    "time": "2020-9-13",
    "tv": "Netflix"
}{
    "href": "/content/meiju25612.html",
    "name": "奇幻沼泽第二季",
    "state": "第17集",
    "time": "2020-9-13",
    "tv": "Disney"
}{
    "href": "/content/meiju25768.html",
    "name": "我最心爱的伊内斯第一季",
    "state": "第4集",
    "time": "2020-9-13",
    "tv": "其他"
}{
    "href": "/content/meiju25820.html",
    "name": "面孔：20世纪传奇人物",
    "state": "全剧完结",
    "time": "2020-9-13",
    "tv": "BBC"
}{
    "href": "/content/meiju24376.html",
    "name": "霹雳娇娃第二季",
    "state": "本季终",
    "time": "2020-9-12",
    "tv": "ABC"
}{
    "href": "/content/meiju25410.html",
    "name": "喧闹一家亲第四季",
    "state": "第8集",
    "time": "2020-9-12",
    "tv": "Nickelodeon"
}{
    "href": "/content/meiju25376.html",
    "name": "女作家与谋杀案第八季",
    "state": "第10集",
    "time": "2020-9-12",
    "tv": "其他"
}{
    "href": "/content/meiju24773.html",
    "name": "新版夏威夷神探第二季",
    "state": "第13集",
    "time": "2020-9-12",
    "tv": "CBS"
}{
    "href": "/content/meiju25725.html",
    "name": "宕机警察第一季",
    "state": "第4集",
    "time": "2020-9-12",
    "tv": "Sky1"
}{
    "href": "/content/meiju25805.html",
    "name": "大麻咖啡馆第二季",
    "state": "本季终",
    "time": "2020-9-12",
    "tv": "Netflix"
}{
    "href": "/content/meiju25819.html",
    "name": "拉利内阿：危城困境第一季",
    "state": "第4集",
    "time": "2020-9-12",
    "tv": "Netflix"
}{
    "href": "/content/meiju25813.html",
    "name": "阿提耶第二季",
    "state": "本季终",
    "time": "2020-9-12",
    "tv": "Netflix"
}{
    "href": "/content/meiju25676.html",
    "name": "神奇蜘蛛侠第一季",
    "state": "第10集",
    "time": "2020-9-11",
    "tv": "CW"
}{
    "href": "/content/meiju25818.html",
    "name": "单亲贵族第一季",
    "state": "本季终",
    "time": "2020-9-11",
    "tv": "Netflix"
}{
    "href": "/content/meiju25817.html",
    "name": "姿态第三季",
    "state": "预告",
    "time": "2020-9-11",
    "tv": "FX"
}{
    "href": "/content/meiju25816.html",
    "name": "芝加哥故事第三季",
    "state": "本季终",
    "time": "2020-9-11",
    "tv": "Showtime"
}{
    "href": "/content/meiju25815.html",
    "name": "性教育第三季",
    "state": "预告",
    "time": "2020-9-11",
    "tv": "：Netflix"
}{
    "href": "/content/meiju25814.html",
    "name": "灵魂伴侣第一季",
    "state": "预告",
    "time": "2020-9-11",
    "tv": "AMC"
}{
    "href": "/content/meiju25811.html",
    "name": "伊敦传奇第一季",
    "state": "本季终",
    "time": "2020-9-10",
    "tv": "Netflix"
}{
    "href": "/content/meiju25810.html",
    "name": "有人非死不可第一季",
    "state": "预告",
    "time": "2020-9-10",
    "tv": "其他"
}{
    "href": "/content/meiju25809.html",
    "name": "我们第一季",
    "state": "预告",
    "time": "2020-9-10",
    "tv": "BBC"
}{
    "href": "/content/meiju25808.html",
    "name": "诸神的黄昏第二季",
    "state": "预告",
    "time": "2020-9-10",
    "tv": "其他"
}{
    "href": "/content/meiju25807.html",
    "name": "教师情事第一季",
    "state": "预告",
    "time": "2020-9-10",
    "tv": "FX"
}{
    "href": "/content/meiju25806.html",
    "name": "移植手术第一季",
    "state": "本季终",
    "time": "2020-9-10",
    "tv": "CTV"
}{
    "href": "/content/meiju25677.html",
    "name": "荒野间谍第二季",
    "state": "本季终",
    "time": "2020-9-10",
    "tv": "BBC"
}{
    "href": "/content/meiju25804.html",
    "name": "生活第一季",
    "state": "预告",
    "time": "2020-9-9",
    "tv": "BBC"
}{
    "href": "/content/meiju25023.html",
    "name": "曼达洛人第二季",
    "state": "预告",
    "time": "2020-9-9",
    "tv": "Disney"
}{
    "href": "/content/meiju25795.html",
    "name": "邻家性士第一季",
    "state": "第8集",
    "time": "2020-9-9",
    "tv": "Quibi"
}{
    "href": "/content/meiju25781.html",
    "name": "溺湾第一季",
    "state": "第3集",
    "time": "2020-9-8",
    "tv": "Acorn"
}{
    "href": "/content/meiju25723.html",
    "name": "乐活姐妹：怪诞冒险第一季",
    "state": "第8集",
    "time": "2020-9-8",
    "tv": "Adult-Swim"
}{
    "href": "/content/meiju25803.html",
    "name": "金牌评论员第四季",
    "state": "本季终",
    "time": "2020-9-8",
    "tv": "TLC"
}{
    "href": "/content/meiju25802.html",
    "name": "李尸朝鲜第三季",
    "state": "预告",
    "time": "2020-9-8",
    "tv": "Netflix"
}{
    "href": "/content/meiju20691.html",
    "name": "国事家事第一季",
    "state": "全剧完结",
    "time": "2020-9-8",
    "tv": "NBC"
}{
    "href": "/content/meiju25611.html",
    "name": "脱衣舞俱乐部第一季",
    "state": "本季终",
    "time": "2020-9-7",
    "tv": "Starz"
}{
    "href": "/content/meiju24157.html",
    "name": "神探默多克第十二季",
    "state": "第10集",
    "time": "2020-9-7",
    "tv": "CBC"
}{
    "href": "/content/meiju25539.html",
    "name": "蜘蛛侠第三季",
    "state": "第4集",
    "time": "2020-9-7",
    "tv": "Disney"
}{
    "href": "/content/meiju25800.html",
    "name": "我们的生活第五季",
    "state": "预告",
    "time": "2020-9-7",
    "tv": "NBC"
}{
    "href": "/content/meiju25801.html",
    "name": "泰坦第三季",
    "state": "预告",
    "time": "2020-9-7",
    "tv": "DCUniverse"
}{
    "href": "/content/meiju25799.html",
    "name": "甜蜜点滴第三季",
    "state": "本季终",
    "time": "2020-9-7",
    "tv": "Netflix"
}{
    "href": "/content/meiju25798.html",
    "name": "甜蜜点滴第二季",
    "state": "第0集",
    "time": "2020-9-7",
    "tv": "Netflix"
}{
    "href": "/content/meiju25797.html",
    "name": "甜蜜点滴第一季",
    "state": "本季终",
    "time": "2020-9-7",
    "tv": "Netflix"
}{
    "href": "/content/meiju25272.html",
    "name": "塔科马消防队第二季",
    "state": "第13集",
    "time": "2020-9-6",
    "tv": "truTV"
}{
    "href": "/content/meiju25773.html",
    "name": "我讨厌苏茜第一季",
    "state": "本季终",
    "time": "2020-9-6",
    "tv": "Sky"
}{
    "href": "/content/meiju25783.html",
    "name": "无笼杀手第一季",
    "state": "本季终",
    "time": "2020-9-5",
    "tv": "Netflix"
}{
    "href": "/content/meiju25755.html",
    "name": "太空克里奥佩特拉第一季",
    "state": "第13集",
    "time": "2020-9-5",
    "tv": "Peacock"
}{
    "href": "/content/meiju25794.html",
    "name": "艾米丽的神奇实验第一季",
    "state": "第10集",
    "time": "2020-9-5",
    "tv": "Netflix"
}{
    "href": "/content/meiju25710.html",
    "name": "谜团实验室第一季",
    "state": "本季终",
    "time": "2020-9-5",
    "tv": "Netflix"
}{
    "href": "/content/meiju25793.html",
    "name": "马萨巴母女第一季",
    "state": "第6集",
    "time": "2020-9-5",
    "tv": "Netflix"
}{
    "href": "/content/meiju25750.html",
    "name": "独角猫！第三季",
    "state": "第22集",
    "time": "2020-9-5",
    "tv": "Cartoon-Network"
}{
    "href": "/content/meiju25792.html",
    "name": "淘气小女巫第三季",
    "state": "全剧完结",
    "time": "2020-9-5",
    "tv": "BBC"
}{
    "href": "/content/meiju25791.html",
    "name": "淘气小女巫第二季",
    "state": "全剧完结",
    "time": "2020-9-5",
    "tv": "BBC"
}